tagdf/__init__.py
tests/__init__.py
tagdf-0.1.0.dist-info/METADATA
tagdf-0.1.0.dist-info/WHEEL
tagdf-0.1.0.dist-info/top_level.txt
tagdf-0.1.0.dist-info/RECORD
