Metadata-Version: 2.4
Name: tagdf
Version: 0.1.0
Summary: Tools for annotating and labelling DataFrames and Python objects
Home-page: https://github.com/idin/tagdf
Author: Idin
Author-email: Idin <py@idin.net>
License: MIT
Project-URL: Homepage, https://github.com/idin/tagdf
Project-URL: Repository, https://github.com/idin/tagdf
Keywords: dataframe,pandas,annotations,labels
Classifier: Development Status :: 3 - Alpha
Classifier: Intended Audience :: Developers
Classifier: License :: OSI Approved :: MIT License
Classifier: Operating System :: OS Independent
Classifier: Programming Language :: Python :: 3
Classifier: Programming Language :: Python :: 3 :: Only
Classifier: Programming Language :: Python :: 3.11
Requires-Python: >=3.11
Dynamic: author
Dynamic: home-page
Dynamic: requires-python
